Metadata-Version: 2.1
Name: knowledgelayer
Version: 0.0
Summary: Knowledge Layer
Author: Delip Rao
Author-email: deliprao@gmail.com
License-File: LICENSE
